Workbook

Sheet 报表封面
A1: 子公司月度运营报表
A2: 长沙运营管理有限公司 | 2026年6月
A4: 报表名称 | B4: 子公司月度运营报表（2026年6月）
A5: 编制单位 | B5: 长沙运营管理有限公司
A6: 所属区域 | B6: 华中
A7: 报告期间 | B7: 2026年6月
A8: 报告类型 | B8: 月度运营分析
A9: 密 级 | B9: 内部资料 · 请勿外传
A10: 法定代表人 | B10: 唐磊
A11: 财务负责人 | B11: 韩雪
A12: 编 制 | B12: 邓超
A13: 编制日期 | B13: 2026-07-15
A15: 目 录
A16: 1. 经营概览
A17: 2. 财务分析
A18: 3. 销售分析
A19: 4. 人力资源
A20: 5. 运营效率
A21: 6. 风险与事项
A23: 数据说明：
A24: 本报表数据来源于各业务系统月度结账结果，金额单位为人民币元；财务、销售、人力、运营各 sheet 间通过公式联动（如经营概览引用财务/销售/人力关键指标）。同比＝本月÷上年同期－1，环比＝本月÷上月－1。占比类指标为结构占比。

Sheet 经营概览
A1: 经营概览 · 关键绩效指标
A2: 2026年6月 | 目标 / 实际 / 达成 / 同比 / 环比
A4: 指标 | B4: 单位 | C4: 目标 | D4: 实际 | E4: 达成率 | F4: 同比 | G4: 环比 | H4: 评价
A5: 营业收入 | B5: 万元 | C5: 2168.9 | D5: ='财务分析'!B27 | E5: =D5/C5 | F5: ='财务分析'!E9 | G5: ='财务分析'!F9 | H5: 目标值由总部核定
A6: 净利润 | B6: 万元 | C6: 265.6 | D6: ='财务分析'!B28 | E6: =D6/C6 | F6: ='财务分析'!E22 | G6: ='财务分析'!F22
A7: 销售净利率 | B7: % | C7: 0.1275 | D7: ='财务分析'!B29 | E7: =D7/C7 | F7: ='财务分析'!E23 | G7: ='财务分析'!F23 | H7: 净利润/营业收入
A8: 销售额达成率 | B8: % | C8: 1 | D8: ='销售分析'!B12 | E8: =D8/C8 | F8: — | G8: — | H8: 实际/目标均值
A9: 人均营收 | B9: 万元/人 | C9: — | D9: ='财务分析'!B27*10000/'人力资源'!E11 | E9: — | F9: — | G9: — | H9: 营收/平均人数
A10: 员工总数 | B10: 人 | C10: 18 | D10: ='人力资源'!E11 | E10: =D10/C10 | F10: — | G10: —
A11: 员工流失率 | B11: % | C11: 0.06 | D11: ='人力资源'!F11 | E11: =D11/C11 | F11: — | G11: — | H11: 越低越好
A12: 客户数 | B12: 家 | C12: 162 | D12: 17 | E12: — | F12: — | G12: —
A13: 订单交付及时率 | B13: % | C13: 0.95 | D13: 0.9526 | E13: — | F13: — | G13: —
A14: 客户满意度 | B14: % | C14: 0.9 | D14: 0.9277 | E14: — | F14: — | G14: —
A15: 研发投入占比 | B15: % | C15: 0.18 | D15: ='财务分析'!B15/'财务分析'!B9 | E15: =D15/C15 | F15: — | G15: — | H15: 研发费用/营收

Sheet 财务分析
A1: 财务分析 · 利润表（月度）
A2: 2026年6月 | 单位：人民币元
A4: 项目 | B4: 本月数 | C4: 上年同期 | D4: 上月数 | E4: 同比 | F4: 环比 | G4: 说明
A5: 产品销售收入 | B5: 10985058 | C5: 9231141 | D5: 11040259 | E5: =(B5-C5)/C5 | F5: =(B5-D5)/D5
A6: 技术服务收入 | B6: 6056810 | C6: 5089756 | D6: 6087246 | E6: =(B6-C6)/C6 | F6: =(B6-D6)/D6
A7: 增值服务收入 | B7: 3262098 | C7: 2741259 | D7: 3278490 | E7: =(B7-C7)/C7 | F7: =(B7-D7)/D7
A8: 其他业务收入 | B8: 1828042 | C8: 1536170 | D8: 1837228 | E8: =(B8-C8)/C8 | F8: =(B8-D8)/D8
A9: 营业收入合计 | B9: =SUM(B5:B8) | C9: =SUM(C5:C8) | D9: =SUM(D5:D8) | E9: =(B9-C9)/C9 | F9: =(B9-D9)/D9
A10: 二、营业成本 | B10: 13954992 | C10: 11726884 | D10: 14025118 | E10: =(B10-C10)/C10 | F10: =(B10-D10)/D10
A11: 税金及附加 | B11: 717609 | C11: 603033 | D11: 721215 | E11: =(B11-C11)/C11 | F11: =(B11-D11)/D11
A12: 三、期间费用 | B12: — | C12: — | D12: — | E12: — | F12: —
A13: 销售费用 | B13: 3834384 | C13: 3222171 | D13: 3853652 | E13: =(B13-C13)/C13 | F13: =(B13-D13)/D13
A14: 管理费用 | B14: 2509832 | C14: 2109103 | D14: 2522444 | E14: =(B14-C14)/C14 | F14: =(B14-D14)/D14
A15: 研发费用 | B15: 4532645 | C15: 3808945 | D15: 4555422 | E15: =(B15-C15)/C15 | F15: =(B15-D15)/D15
A16: 财务费用 | B16: -326772 | C16: -274598 | D16: -328414 | E16: =(B16-C16)/C16 | F16: =(B16-D16)/D16
A17: 期间费用合计 | B17: =SUM(B13:B16) | C17: =SUM(C13:C16) | D17: =SUM(D13:D16) | E17: =(B17-C17)/C17 | F17: =(B17-D17)/D17
A18: 四、营业利润 | B18: =B9-B10-B11-B17 | C18: =C9-C10-C11-C17 | D18: =D9-D10-D11-D17 | E18: =(B18-C18)/C18 | F18: =(B18-D18)/D18
A19: 营业外收支净额 | B19: 340304 | C19: 285970 | D19: 342014 | E19: =(B19-C19)/C19 | F19: =(B19-D19)/D19
A20: 五、利润总额 | B20: =B18+B19 | C20: =C18+C19 | D20: =D18+D19 | E20: =(B20-C20)/C20 | F20: =(B20-D20)/D20
A21: 所得税费用 | B21: =B20*0.15 | C21: =C20*0.15 | D21: =D20*0.15 | E21: — | F21: —
A22: 六、净利润 | B22: =B20-B21 | C22: =C20-C21 | D22: =D20-D21 | E22: =(B22-C22)/C22 | F22: =(B22-D22)/D22
A23: 销售净利率 | B23: =B22/B9 | C23: — | D23: — | E23: — | F23: —
A24: 营业利润率 | B24: =B18/B9 | C24: — | D24: — | E24: — | F24: —
A26: 关键指标汇总（本月）
A27: 营业收入(万元) | B27: =B9/10000
A28: 净利润(万元) | B28: =B22/10000
A29: 销售净利率(%) | B29: =B22/B9
A30: 营业利润率(%) | B30: =B18/B9

Sheet 销售分析
A1: 销售分析 · 产品线 / 区域
A2: 2026年6月 | 单位：人民币元
A4: 产品 | B4: 目标销售额 | C4: 实际销售额 | D4: 达成率 | E4: 上年同期 | F4: 上月 | G4: 同比 | H4: 环比
A5: 标准版软件 | B5: 4706031 | C5: 5010641 | D5: =C5/B5 | E5: 4210623 | F5: 5035820 | G5: =(C5-E5)/E5 | H5: =(C5-F5)/F5
A6: 企业版软件 | B6: 3461701 | C6: 3565931 | D6: =C6/B6 | E6: 2996581 | F6: 3583850 | G6: =(C6-E6)/E6 | H6: =(C6-F6)/F6
A7: 定制开发服务 | B7: 2962109 | C7: 2948496 | D7: =C7/B7 | E7: 2477728 | F7: 2963313 | G7: =(C7-E7)/E7 | H7: =(C7-F7)/F7
A8: 运维支持服务 | B8: 2534213 | C8: 2379402 | D8: =C8/B8 | E8: 1999497 | F8: 2391359 | G8: =(C8-E8)/E8 | H8: =(C8-F8)/F8
A9: 云订阅(SaaS) | B9: 2794157 | C9: 2809284 | D9: =C9/B9 | E9: 2360743 | F9: 2823401 | G9: =(C9-E9)/E9 | H9: =(C9-F9)/F9
A12: 整体销售额达成率 | B12: =AVERAGE(D5:D9)
A14: 区域销售额分布
A15: 区域 | B15: 销售额 | C15: 占比
A16: 本地市场 | B16: 5938990 | C16: =B16/$B$20
A17: 周边省份 | B17: 4436900 | C17: =B17/$B$20
A18: 线上直销 | B18: 3160798 | C18: =B18/$B$20
A19: 渠道代理 | B19: 2623183 | C19: =B19/$B$20
A20: 合计 | B20: =SUM(B16:B19) | C20: =SUM(C16:C19)

Sheet 人力资源
A1: 人力资源 · 编制与流动
A2: 2026年6月 | 单位：人 / %
A4: 部门 | B4: 月初人数 | C4: 入职 | D4: 离职 | E4: 月末人数 | F4: 流失率
A5: 研发部 | B5: 7 | C5: 1 | D5: 1 | E5: =B5+C5-D5 | F5: =D5/((B5+E5)/2)
A6: 销售部 | B6: 4 | C6: 0 | D6: 0 | E6: =B6+C6-D6 | F6: =D6/((B6+E6)/2)
A7: 实施部 | B7: 3 | C7: 0 | D7: 0 | E7: =B7+C7-D7 | F7: =D7/((B7+E7)/2)
A8: 客服部 | B8: 2 | C8: 0 | D8: 1 | E8: =B8+C8-D8 | F8: =D8/((B8+E8)/2)
A9: 职能部门 | B9: 2 | C9: 1 | D9: 1 | E9: =B9+C9-D9 | F9: =D9/((B9+E9)/2)
A10: 管理层 | B10: 2 | C10: 1 | D10: 1 | E10: =B10+C10-D10 | F10: =D10/((B10+E10)/2)
A11: 合计 / 平均 | B11: =SUM(B5:B10) | C11: =SUM(C5:C10) | D11: =SUM(D5:D10) | E11: =SUM(E5:E10) | F11: =D11/((B11+E11)/2)
A13: 招聘与培训
A14: 招聘需求(人) | B14: 8
A15: 已到岗(人) | B15: 4
A16: 招聘完成率 | B16: =B15/B14
A17: 人均培训时长(小时) | B17: 28.1

Sheet 运营效率
A1: 运营效率 · 关键运营指标
A2: 2026年6月 | 本月值与目标对比
A4: 指标 | B4: 本月值 | C4: 目标 | D4: 达成率 | E4: 备注
A5: 服务工单处理量(单) | B5: 1563 | C5: 1980 | D5: =B5/C5 | E5: 含实施与客服工单
A6: 产能/人效利用率 | B6: 0.7817 | C6: 0.9 | D6: =B6/C6 | E6: 实际产出/标准产能
A7: 库存周转天数(天) | B7: 44 | C7: 35 | D7: =C7/B7 | E7: 越低越好
A8: 交付物良品率 | B8: 0.9919 | C8: 0.985 | D8: =B8/C8 | E8: 一次验收通过率
A9: 设备综合效率OEE | B9: 0.7749 | C9: 0.85 | D9: =B9/C9
A10: 订单交付及时率 | B10: 0.9526 | C10: 0.95 | D10: =B10/C10
A11: 客户满意度(CSAT) | B11: 0.9277 | C11: 0.9 | D11: =B11/C11 | E11: 回收样本满意度均值
A12: 工单处理及时率 | B12: 0.9322 | C12: 0.95 | D12: =B12/C12

Sheet 风险与事项
A1: 风险与事项跟踪
A2: 2026年6月 | 重点经营风险与应对
A4: 序号 | B4: 风险/事项 | C4: 类别 | D4: 责任部门 | E4: 责任人 | F4: 等级 | G4: 状态 | H4: 应对措施 | I4: 截止日期
A5: 1 | B5: 核心研发人员流失风险 | C5: 人才 | D5: 人才部 | E5: 研发部负责人 | F5: 高 | G5: 进行中 | H5: 优化薪酬包并启动关键岗位继任计划 | I5: 2026-08-31
A6: 2 | B6: 大客户续约谈判滞后 | C6: 客户 | D6: 客户部 | E6: 销售总监 | F6: 中 | G6: 进行中 | H6: 高管介入并给出阶梯折扣方案 | I6: 2026-07-30
A7: 3 | B7: 交付工期压力上升 | C7: 交付 | D7: 交付部 | E7: 实施负责人 | F7: 中 | G7: 监控中 | H7: 引入外部协作资源并排期优化 | I7: 2026-08-15
A8: 4 | B8: 成本费用率高于目标 | C8: 财务 | D8: 财务部 | E8: 韩雪 | F8: 中 | G8: 进行中 | H8: 压缩非必要差旅与外包支出 | I8: 2026-09-30
A9: 5 | B9: 数据安全合规待加固 | C9: 合规 | D9: 合规部 | E9: 技术负责人 | F9: 高 | G9: 规划中 | H9: 完成等保二级整改与渗透测试 | I9: 2026-10-31
